LICENSE
MANIFEST.in
README.md
requirements.txt
setup.py
src/pii_data/__init__.py
src/pii_data/defs.py
src/pii_data.egg-info/PKG-INFO
src/pii_data.egg-info/SOURCES.txt
src/pii_data.egg-info/dependency_links.txt
src/pii_data.egg-info/entry_points.txt
src/pii_data.egg-info/requires.txt
src/pii_data.egg-info/top_level.txt
src/pii_data/app/__init__.py
src/pii_data/app/rawdoc.py
src/pii_data/dump/__init__.py
src/pii_data/dump/json.py
src/pii_data/dump/text.py
src/pii_data/dump/utils.py
src/pii_data/dump/yaml.py
src/pii_data/helper/__init__.py
src/pii_data/helper/config.py
src/pii_data/helper/exception.py
src/pii_data/helper/io.py
src/pii_data/helper/json_encoder.py
src/pii_data/helper/logger.py
src/pii_data/helper/misc.py
src/pii_data/helper/peeker.py
src/pii_data/types/__init__.py
src/pii_data/types/piientity.py
src/pii_data/types/piienum.py
src/pii_data/types/doc/__init__.py
src/pii_data/types/doc/chunker.py
src/pii_data/types/doc/defs.py
src/pii_data/types/doc/document.py
src/pii_data/types/doc/localdoc.py
src/pii_data/types/piicollection/__init__.py
src/pii_data/types/piicollection/chunk.py
src/pii_data/types/piicollection/collection.py
src/pii_data/types/piicollection/loader.py