Metadata-Version: 2.1
Name: pii-data
Version: 0.5.0
Summary: Base data structures for PII Processing
Home-page: https://github.com/piisa/pii-data
Download-URL: https://github.com/piisa/pii-data/tarball/v0.5.0
Author: Paulo Villegas
Author-email: paulo.vllgs@gmail.com
License: Apache
Keywords: PIISA, PII
Classifier: Programming Language :: Python :: 3 :: Only
Classifier: License :: OSI Approved :: Apache Software License
Classifier: Development Status :: 4 - Beta
Classifier: Topic :: Software Development :: Libraries :: Application Frameworks
Requires-Python: >=3.8
Provides-Extra: test
License-File: LICENSE
